kenl380/pylib/__init__.py
kenl380/pylib/__version__.py
kenl380/pylib/pylib.py
kenl380.pylib-1.0.0.dist-info/METADATA
kenl380.pylib-1.0.0.dist-info/RECORD
kenl380.pylib-1.0.0.dist-info/WHEEL
kenl380.pylib-1.0.0.dist-info/top_level.txt
