Metadata-Version: 2.1
Name: kenl380.pylib
Version: 1.0.0
Summary: Python Library for common code used across my packages.
Home-page: https://github.com/kenlowrie/pylib
Author: Ken Lowrie
Author-email: ken@kenlowrie.com
License: Apache 2.0
Platform: UNKNOWN
Classifier: Development Status :: 4 - Beta
Classifier: License :: OSI Approved :: Apache Software License
Classifier: Programming Language :: Python
Classifier: Programming Language :: Python :: 2.7
Classifier: Programming Language :: Python :: 3
Classifier: Programming Language :: Python :: 3.6
Classifier: Programming Language :: Python :: 3.7
Requires-Python: >=2.7
Requires-Dist: kenl380
